[
    {
        "id": "19022005669@s.whatsapp.net",
        "verified": false,
        "name": "Bakchod Raja",
        "time": "19/11 17:54:30",
        "limit": 0,
        "balance": 0,
        "premium": false
    },
    {
        "id": "917780903638@s.whatsapp.net",
        "verified": false,
        "name": "Gunpreet Singh",
        "time": "19/11 18:10:55",
        "limit": 0,
        "balance": 0,
        "premium": false
    },
    {
        "id": "919682529593@s.whatsapp.net",
        "verified": false,
        "name": "Kurt Cocaine",
        "time": "10/12 01:27:30",
        "limit": 0,
        "balance": 0,
        "premium": false
    },
    {
        "id": "917780896154@s.whatsapp.net",
        "verified": false,
        "name": "Vinay",
        "time": "10/12 01:27:30",
        "limit": 0,
        "balance": 0,
        "premium": false
    },
    {
        "id": "919596849211@s.whatsapp.net",
        "verified": false,
        "name": "Shubam Salaria",
        "time": "10/12 01:27:30",
        "limit": 0,
        "balance": 0,
        "premium": false
    },
    {
        "id": "628159873884@s.whatsapp.net",
        "verified": false,
        "name": "Risa",
        "time": "10/12 01:28:12",
        "limit": 0,
        "balance": 0,
        "premium": false
    }
]